llama_index/program/evaporate/__init__.py
llama_index/program/evaporate/base.py
llama_index/program/evaporate/df.py
llama_index/program/evaporate/extractor.py
llama_index/program/evaporate/prompts.py
llama_index_program_evaporate-0.5.1.dist-info/METADATA
llama_index_program_evaporate-0.5.1.dist-info/WHEEL
llama_index_program_evaporate-0.5.1.dist-info/licenses/LICENSE
llama_index_program_evaporate-0.5.1.dist-info/RECORD
